eldom/__init__.py
eldom/client.py
eldom/constants.py
eldom/convector_heater.py
eldom/flat_boiler.py
eldom/models.py
eldom/smart_boiler.py
ioteldom/__init__.py
ioteldom/client.py
ioteldom/constants.py
ioteldom/convector_heater.py
ioteldom/crc.py
ioteldom/crypto.py
ioteldom/flat_boiler.py
ioteldom/models.py
ioteldom/token.py
ioteldom/token_provider.py
pyeldom-2.0.1.dist-info/licenses/LICENSE
tests/__init__.py
pyeldom-2.0.1.dist-info/METADATA
pyeldom-2.0.1.dist-info/WHEEL
pyeldom-2.0.1.dist-info/top_level.txt
pyeldom-2.0.1.dist-info/RECORD
