Metadata-Version: 2.4
Name: pyeldom
Version: 2.0.1
Summary: A Python client for the Eldom API
Home-page: https://github.com/qbaware/pyeldom
Author: Daniel Gospodinow
Author-email: danielgospodinow@gmail.com
Classifier: Programming Language :: Python :: 3
Classifier: License :: OSI Approved :: MIT License
Classifier: Operating System :: OS Independent
Requires-Python: >=3.6
License-File: LICENSE
Requires-Dist: requests
Dynamic: author
Dynamic: author-email
Dynamic: classifier
Dynamic: description
Dynamic: description-content-type
Dynamic: home-page
Dynamic: license-file
Dynamic: requires-dist
Dynamic: requires-python
Dynamic: summary
